{
  "meta": {
    "company_name": "Dell Technologies Inc.",
    "ticker": "DELL",
    "extraction_date": "2025-01-07",
    "baseline_fiscal_year": 2024,
    "data_freshness_note": "Based on FY2024 10-K filed March 2024, supplemented with Q3 FY2025 earnings",
    "confidence_overall": 0.78,
    "primary_sources": [
      "Dell Technologies 10-K FY2024",
      "Dell Technologies Q3 FY2025 Earnings Call",
      "Dell Investor Day 2024 Presentation",
      "Industry analyst reports (Gartner, IDC)"
    ]
  },

  "company_overview": {
    "headquarters": {"city": "Round Rock, Texas", "country": "USA"},
    "founded": 1984,
    "employees": 120000,
    "business_description": "Dell Technologies is a global technology company that designs, develops, manufactures, markets, sells, and supports information technology solutions, products, and services. The company operates through two main segments: Infrastructure Solutions Group (ISG) and Client Solutions Group (CSG).",
    "business_model": "hybrid",
    "primary_segments": [
      {
        "name": "Client Solutions Group (CSG)",
        "revenue_percent": 55,
        "description": "Commercial and consumer PCs, notebooks, workstations, and peripherals"
      },
      {
        "name": "Infrastructure Solutions Group (ISG)",
        "revenue_percent": 40,
        "description": "Servers, storage, networking, and related services including AI infrastructure"
      },
      {
        "name": "Other",
        "revenue_percent": 5,
        "description": "Software, peripherals, and third-party services"
      }
    ],
    "value_chain_position": "midstream"
  },

  "geographic_exposure": {
    "revenue_by_region": [
      {
        "region": "Americas",
        "percent_of_total": 52,
        "revenue_usd_millions": 45968,
        "yoy_growth": 3.2,
        "source_tier": 1
      },
      {
        "region": "Europe, Middle East, Africa (EMEA)",
        "percent_of_total": 28,
        "revenue_usd_millions": 24752,
        "yoy_growth": -2.1,
        "source_tier": 1
      },
      {
        "region": "Asia Pacific & Japan (APJ)",
        "percent_of_total": 20,
        "revenue_usd_millions": 17680,
        "yoy_growth": -5.4,
        "source_tier": 1
      }
    ],
    "manufacturing_footprint": [
      {
        "country": "China",
        "percent_of_production": 40,
        "facility_types": ["manufacturing", "assembly"],
        "notes": "Primary manufacturing hub through contract manufacturers; Xiamen and Chengdu facilities",
        "source_tier": 2
      },
      {
        "country": "Malaysia",
        "percent_of_production": 25,
        "facility_types": ["manufacturing", "assembly"],
        "notes": "Penang facility - key alternative to China operations",
        "source_tier": 2
      },
      {
        "country": "USA",
        "percent_of_production": 15,
        "facility_types": ["manufacturing", "assembly", "customization"],
        "notes": "Austin, TX - primarily enterprise and custom configurations",
        "source_tier": 2
      },
      {
        "country": "Mexico",
        "percent_of_production": 12,
        "facility_types": ["manufacturing", "assembly"],
        "notes": "Expanding capacity for USMCA benefits",
        "source_tier": 2
      },
      {
        "country": "Brazil",
        "percent_of_production": 5,
        "facility_types": ["assembly"],
        "notes": "Regional assembly for Latin America",
        "source_tier": 3
      },
      {
        "country": "Poland",
        "percent_of_production": 3,
        "facility_types": ["assembly", "customization"],
        "notes": "European regional hub",
        "source_tier": 3
      }
    ],
    "key_facilities": [
      {
        "name": "Round Rock Campus",
        "location": {"city": "Round Rock", "country": "USA"},
        "type": "headquarters",
        "function": "Global headquarters, executive offices, R&D",
        "significance": "Command center for global operations, houses key decision-making",
        "source_tier": 1
      },
      {
        "name": "Xiamen Manufacturing",
        "location": {"city": "Xiamen", "country": "China"},
        "type": "manufacturing",
        "function": "PC and server assembly",
        "significance": "Largest manufacturing facility, ~25% of total production",
        "source_tier": 2
      },
      {
        "name": "Penang Operations",
        "location": {"city": "Penang", "country": "Malaysia"},
        "type": "manufacturing",
        "function": "Server and storage manufacturing",
        "significance": "Primary non-China manufacturing hub, strategic diversification",
        "source_tier": 2
      },
      {
        "name": "Austin Manufacturing",
        "location": {"city": "Austin", "country": "USA"},
        "type": "manufacturing",
        "function": "Enterprise servers, custom configurations",
        "significance": "Made-in-USA capability for federal and security-sensitive customers",
        "source_tier": 2
      },
      {
        "name": "Limerick Campus",
        "location": {"city": "Limerick", "country": "Ireland"},
        "type": "r_and_d",
        "function": "EMEA headquarters, software development, customer support",
        "significance": "European hub for operations and R&D",
        "source_tier": 2
      }
    ]
  },

  "supply_chain": {
    "critical_suppliers": [
      {
        "name": "Intel Corporation",
        "headquarters_country": "USA",
        "provides": "CPUs for PCs and servers (x86 processors)",
        "dependency_level": "critical",
        "single_source": false,
        "notes": "Primary CPU supplier; AMD is alternative but Intel dominates enterprise",
        "source_tier": 2
      },
      {
        "name": "AMD (Advanced Micro Devices)",
        "headquarters_country": "USA",
        "provides": "CPUs and GPUs for PCs and servers",
        "dependency_level": "high",
        "single_source": false,
        "notes": "Growing share in server CPUs (EPYC), secondary PC CPU supplier",
        "source_tier": 2
      },
      {
        "name": "NVIDIA Corporation",
        "headquarters_country": "USA",
        "provides": "GPUs for AI servers, workstations, gaming",
        "dependency_level": "critical",
        "single_source": true,
        "notes": "Near-monopoly on AI/ML accelerators; H100/B200 GPUs critical for AI server demand",
        "source_tier": 2
      },
      {
        "name": "Samsung Electronics",
        "headquarters_country": "South Korea",
        "provides": "DRAM, NAND flash memory, SSDs",
        "dependency_level": "high",
        "single_source": false,
        "notes": "One of three major memory suppliers (with SK Hynix, Micron)",
        "source_tier": 2
      },
      {
        "name": "SK Hynix",
        "headquarters_country": "South Korea",
        "provides": "DRAM, NAND flash, HBM for AI",
        "dependency_level": "high",
        "single_source": false,
        "notes": "Critical for HBM (High Bandwidth Memory) for AI servers",
        "source_tier": 2
      },
      {
        "name": "Micron Technology",
        "headquarters_country": "USA",
        "provides": "DRAM, NAND flash memory",
        "dependency_level": "high",
        "single_source": false,
        "notes": "US-based memory supplier; diversification from Korean suppliers",
        "source_tier": 2
      },
      {
        "name": "TSMC (Taiwan Semiconductor)",
        "headquarters_country": "Taiwan",
        "provides": "Semiconductor fabrication (indirect - via Intel, NVIDIA, AMD)",
        "dependency_level": "critical",
        "single_source": true,
        "notes": "Not direct supplier but manufactures chips for key suppliers; single point of failure for advanced nodes",
        "source_tier": 2
      },
      {
        "name": "Microsoft Corporation",
        "headquarters_country": "USA",
        "provides": "Windows OS licenses, software ecosystem",
        "dependency_level": "critical",
        "single_source": true,
        "notes": "Windows pre-installed on virtually all Dell PCs; no viable alternative for enterprise",
        "source_tier": 2
      }
    ],
    "contract_manufacturers": [
      {
        "name": "Foxconn (Hon Hai)",
        "headquarters_country": "Taiwan",
        "production_countries": ["China", "Vietnam", "India", "Mexico"],
        "products_manufactured": "Consumer PCs, monitors, some servers",
        "source_tier": 2
      },
      {
        "name": "Wistron",
        "headquarters_country": "Taiwan",
        "production_countries": ["China", "Taiwan", "India"],
        "products_manufactured": "Notebooks, desktop PCs",
        "source_tier": 2
      },
      {
        "name": "Compal Electronics",
        "headquarters_country": "Taiwan",
        "production_countries": ["China", "Vietnam"],
        "products_manufactured": "Notebooks, monitors",
        "source_tier": 2
      },
      {
        "name": "Quanta Computer",
        "headquarters_country": "Taiwan",
        "production_countries": ["China", "Taiwan"],
        "products_manufactured": "Servers, cloud infrastructure",
        "source_tier": 2
      }
    ],
    "supplier_geography_concentration": {
      "top_country": "Taiwan",
      "top_country_percent": 45,
      "top_3_countries": ["Taiwan", "China", "South Korea"],
      "concentration_note": "Heavy reliance on Taiwan (TSMC, ODMs) and China (manufacturing). Korean memory suppliers diversify somewhat but still concentrated in East Asia."
    }
  },

  "customer_profile": {
    "segment_mix": {
      "b2b_percent": 75,
      "b2c_percent": 20,
      "b2g_percent": 5
    },
    "top_customers": [
      {
        "name": "Undisclosed - Large Cloud Provider A",
        "percent_of_revenue": null,
        "industry": "Cloud/Hyperscaler",
        "source_tier": 3
      },
      {
        "name": "Undisclosed - Federal Government",
        "percent_of_revenue": null,
        "industry": "Government",
        "source_tier": 3
      }
    ],
    "customer_concentration": {
      "top_customer_percent": null,
      "top_10_percent": null,
      "concentration_level": "low",
      "note": "Dell does not disclose individual customer concentration; diversified across enterprise, SMB, consumer, and government segments"
    },
    "industry_exposure": [
      {"industry": "Enterprise IT", "percent_of_revenue": 45},
      {"industry": "Small & Medium Business", "percent_of_revenue": 20},
      {"industry": "Consumer", "percent_of_revenue": 20},
      {"industry": "Government & Education", "percent_of_revenue": 10},
      {"industry": "Healthcare", "percent_of_revenue": 5}
    ]
  },

  "regulatory_footprint": {
    "primary_jurisdictions": [
      {
        "jurisdiction": "United States",
        "regulatory_bodies": ["SEC", "FTC", "CFIUS", "BIS"],
        "key_requirements": ["Public company reporting", "Export controls (EAR)", "Antitrust", "Foreign investment review"],
        "exposure_level": "high"
      },
      {
        "jurisdiction": "European Union",
        "regulatory_bodies": ["European Commission", "National DPAs"],
        "key_requirements": ["GDPR compliance", "Digital Services Act", "CE marking", "Sustainability reporting"],
        "exposure_level": "high"
      },
      {
        "jurisdiction": "China",
        "regulatory_bodies": ["MIIT", "CAC", "SAMR"],
        "key_requirements": ["Data localization", "Cybersecurity law", "Multi-Level Protection Scheme"],
        "exposure_level": "high"
      }
    ],
    "trade_exposure": {
      "tariff_exposure": {
        "level": "high",
        "key_tariffs": [
          "Section 301 tariffs on China imports (7.5-25%)",
          "Potential future tariff escalation under new administration"
        ],
        "notes": "Significant exposure due to China manufacturing concentration; some tariff exclusions obtained"
      },
      "export_controls": {
        "level": "high",
        "applicable_regimes": ["EAR", "Entity List restrictions"],
        "notes": "AI server exports to China restricted; affects high-margin AI infrastructure sales"
      },
      "sanctions_exposure": {
        "level": "medium",
        "notes": "Standard compliance program; no significant exposure to sanctioned entities disclosed"
      }
    },
    "compliance_domains": ["data_privacy", "export_controls", "environmental", "labor", "product_safety", "financial_reporting"]
  },

  "financial_baseline": {
    "fiscal_year": 2024,
    "revenue_usd_millions": 88400,
    "gross_margin": 0.223,
    "operating_margin": 0.056,
    "net_margin": 0.035,
    "market_cap_usd_millions": 75000,
    "cash_position_usd_millions": 7400,
    "total_debt_usd_millions": 24700,
    "debt_to_equity": 3.2,
    "current_ratio": 0.78,
    "balance_sheet_strength": "adequate",
    "source_tier": 1
  },

  "strategic_initiatives": [
    {
      "name": "AI Infrastructure Expansion",
      "type": "expansion",
      "description": "Aggressive expansion of AI server portfolio with NVIDIA GPU integration; targeting hyperscalers and enterprise AI adoption",
      "status": "in_progress",
      "geographic_relevance": "Global, with US focus due to export controls on China",
      "source_tier": 1
    },
    {
      "name": "Supply Chain Diversification",
      "type": "supply_chain",
      "description": "Expanding manufacturing in Vietnam and Mexico to reduce China concentration",
      "status": "in_progress",
      "geographic_relevance": "Shift from China to Vietnam, Mexico, India",
      "source_tier": 2
    },
    {
      "name": "APEX as-a-Service Growth",
      "type": "transformation",
      "description": "Expanding APEX subscription/consumption model for infrastructure",
      "status": "in_progress",
      "geographic_relevance": "Global",
      "source_tier": 1
    },
    {
      "name": "Federal Business Expansion",
      "type": "expansion",
      "description": "Growing federal government IT contracts; leveraging US manufacturing capability",
      "status": "in_progress",
      "geographic_relevance": "USA",
      "source_tier": 2
    }
  ],

  "concentration_flags": [
    {
      "flag_type": "manufacturing",
      "description": "40% of manufacturing concentrated in China",
      "severity": "high",
      "details": "Primary manufacturing through contract manufacturers in Xiamen and Chengdu regions; vulnerable to US-China trade tensions and potential supply disruption"
    },
    {
      "flag_type": "supplier",
      "description": "Critical dependency on Taiwan semiconductor ecosystem",
      "severity": "high",
      "details": "TSMC fabricates chips for key suppliers (Intel, NVIDIA, AMD); Taiwan contract manufacturers (Foxconn, Wistron, Compal) handle significant production volume"
    },
    {
      "flag_type": "supplier",
      "description": "NVIDIA near-monopoly on AI accelerators",
      "severity": "high",
      "details": "AI server demand dependent on NVIDIA GPU supply; limited alternatives for high-performance AI training"
    },
    {
      "flag_type": "supplier",
      "description": "Memory supplier concentration in East Asia",
      "severity": "medium",
      "details": "Samsung, SK Hynix (Korea) and Micron (US, but Asian fabs) dominate memory supply; HBM for AI particularly concentrated"
    },
    {
      "flag_type": "regulatory",
      "description": "Export control exposure on AI products to China",
      "severity": "medium",
      "details": "BIS restrictions on advanced AI chip exports to China limit high-margin server sales to second-largest market"
    }
  ],

  "data_quality": {
    "completeness_score": 0.78,
    "data_gaps": [
      "Specific customer revenue concentration not disclosed",
      "Precise manufacturing capacity by facility not public",
      "Tier 2/3 supplier visibility limited",
      "Contract manufacturer revenue allocation not disclosed"
    ],
    "stale_data_warnings": [
      "FY2024 10-K data is baseline; some metrics may have shifted in FY2025"
    ],
    "source_summary": {
      "tier_1_count": 12,
      "tier_2_count": 28,
      "tier_3_count": 8,
      "tier_4_count": 2
    }
  }
}
